dpaste/__init__.py
dpaste/apps.py
dpaste/forms.py
dpaste/highlight.py
dpaste/models.py
dpaste/views.py
dpaste/wsgi.py
dpaste/management/__init__.py
dpaste/management/commands/__init__.py
dpaste/management/commands/cleanup_snippets.py
dpaste/migrations/0001_initial.py
dpaste/migrations/0002_auto_20170119_1038.py
dpaste/migrations/0003_snippet_highlighted.py
dpaste/migrations/0004_auto_20180107_1603.py
dpaste/migrations/0005_remove_snippet_highlighted.py
dpaste/migrations/0006_auto_20180622_1051.py
dpaste/migrations/0007_snippet_rtl.py
dpaste/migrations/__init__.py
dpaste/settings/__init__.py
dpaste/settings/base.py
dpaste/settings/local.py
dpaste/settings/tests.py
dpaste/static/dpaste.css
dpaste/static/dpaste.css.map
dpaste/static/dpaste.js
dpaste/templates/dpaste/404.html
dpaste/templates/dpaste/500.html
dpaste/templates/dpaste/about.html
dpaste/templates/dpaste/base.html
dpaste/templates/dpaste/details.html
dpaste/templates/dpaste/details_slim.html
dpaste/templates/dpaste/history.html
dpaste/templates/dpaste/new.html
dpaste/templates/dpaste/raw.html
dpaste/templates/dpaste/highlight/code.html
dpaste/templates/dpaste/highlight/text.html
dpaste/templates/dpaste/includes/diff.html
dpaste/templates/dpaste/includes/form.html
dpaste/tests/__init__.py
dpaste/tests/test_api.py
dpaste/tests/test_highlight.py
dpaste/tests/test_snippet.py
dpaste/urls/__init__.py
dpaste/urls/dpaste.py
dpaste/urls/dpaste_api.py
dpaste-3.5.dist-info/LICENSE
dpaste-3.5.dist-info/METADATA
dpaste-3.5.dist-info/WHEEL
dpaste-3.5.dist-info/top_level.txt
dpaste-3.5.dist-info/RECORD
