Metadata-Version: 2.1
Name: dpaste
Version: 3.5
Summary: A Django based pastebin for text and code.
Home-page: https://github.com/bartTC/dpaste
Author: Martin Mahner
Author-email: martin@mahner.org
License: MIT
Keywords: django,pastebin
Platform: UNKNOWN
Classifier: Development Status :: 5 - Production/Stable
Classifier: Environment :: Web Environment
Classifier: Intended Audience :: Developers
Classifier: License :: OSI Approved :: MIT License
Classifier: Operating System :: OS Independent
Classifier: Programming Language :: Python
Classifier: Programming Language :: Python :: 3.6
Classifier: Programming Language :: Python :: 3.7
Classifier: Programming Language :: Python :: 3.8
Classifier: Framework :: Django
Requires-Python: >=3.6
Requires-Dist: django (>=2.2)
Requires-Dist: pygments (>=1.6)
Requires-Dist: django-staticinline (>=1.0)
Requires-Dist: django-csp (>=3.6)
Requires-Dist: dj-database-url (>=0.5.0)
Requires-Dist: jsx-lexer (>=0.0.8)
Requires-Dist: misaka (>=2.1.0)
Requires-Dist: docutils
Requires-Dist: tox
Requires-Dist: pytest
Requires-Dist: pytest-cov
Requires-Dist: pytest-django
Provides-Extra: dev
Requires-Dist: ipdb ; extra == 'dev'
Requires-Dist: isort ; extra == 'dev'
Requires-Dist: black ; extra == 'dev'
Requires-Dist: sphinx ; extra == 'dev'
Requires-Dist: sphinx-autobuild ; extra == 'dev'
Requires-Dist: sphinx-rtd-theme ; extra == 'dev'
Requires-Dist: sphinx-press-theme ; extra == 'dev'
Requires-Dist: sphinxcontrib-httpdomain ; extra == 'dev'
Provides-Extra: production
Requires-Dist: psycopg2-binary (==2.8.4) ; extra == 'production'
Requires-Dist: django-webserver[pyuwsgi] (==1.1.0) ; extra == 'production'
